[
    {
        "email": "ZeEithXhG32iYrYLYVu5JJjW@hotmail.com",
        "password": "KCE)k6#P,ke(J6>0",
        "response": {
            "appId": "PXaOtQIWNf",
            "jsClientSrc": "/aOtQIWNf/init.js",
            "firstPartyEnabled": true,
            "vid": "4ed03879-33e0-11ef-81a0-c7eb5e4c559b",
            "uuid": "4ea96570-33e0-11ef-a5db-8dbf8345be5d",
            "hostUrl": "/aOtQIWNf/xhr",
            "blockScript": "/aOtQIWNf/captcha/captcha.js?a=c&u=4ea96570-33e0-11ef-a5db-8dbf8345be5d&v=4ed03879-33e0-11ef-81a0-c7eb5e4c559b&m=0",
            "altBlockScript": "https://captcha.px-cloud.net/PXaOtQIWNf/captcha.js?a=c&u=4ea96570-33e0-11ef-a5db-8dbf8345be5d&v=4ed03879-33e0-11ef-81a0-c7eb5e4c559b&m=0",
            "customLogo": "https://chegg-mobile-promotions.cheggcdn.com/px/Chegg-logo-79X22.png"
        }
    },
    {
        "email": "tXketJ8AqUqclehjtKR2@hotmail.com",
        "password": "G]e:2^qZ,)OecM7;",
        "response": {
            "appId": "PXaOtQIWNf",
            "jsClientSrc": "/aOtQIWNf/init.js",
            "firstPartyEnabled": true,
            "vid": "4ed03879-33e0-11ef-81a0-c7eb5e4c559b",
            "uuid": "4ea96570-33e0-11ef-a5db-8dbf8345be5d",
            "hostUrl": "/aOtQIWNf/xhr",
            "blockScript": "/aOtQIWNf/captcha/captcha.js?a=c&u=4ea96570-33e0-11ef-a5db-8dbf8345be5d&v=4ed03879-33e0-11ef-81a0-c7eb5e4c559b&m=0",
            "altBlockScript": "https://captcha.px-cloud.net/PXaOtQIWNf/captcha.js?a=c&u=4ea96570-33e0-11ef-a5db-8dbf8345be5d&v=4ed03879-33e0-11ef-81a0-c7eb5e4c559b&m=0",
            "customLogo": "https://chegg-mobile-promotions.cheggcdn.com/px/Chegg-logo-79X22.png"
        }
    },
    {
        "email": "4Jk0NUds0zH621n6KfAZKhti3db7@hotmail.com",
        "password": "\\K1++NXJMl~WZ.{,",
        "response": {
            "appId": "PXaOtQIWNf",
            "jsClientSrc": "/aOtQIWNf/init.js",
            "firstPartyEnabled": true,
            "vid": "4ed03879-33e0-11ef-81a0-c7eb5e4c559b",
            "uuid": "4ea96570-33e0-11ef-a5db-8dbf8345be5d",
            "hostUrl": "/aOtQIWNf/xhr",
            "blockScript": "/aOtQIWNf/captcha/captcha.js?a=c&u=4ea96570-33e0-11ef-a5db-8dbf8345be5d&v=4ed03879-33e0-11ef-81a0-c7eb5e4c559b&m=0",
            "altBlockScript": "https://captcha.px-cloud.net/PXaOtQIWNf/captcha.js?a=c&u=4ea96570-33e0-11ef-a5db-8dbf8345be5d&v=4ed03879-33e0-11ef-81a0-c7eb5e4c559b&m=0",
            "customLogo": "https://chegg-mobile-promotions.cheggcdn.com/px/Chegg-logo-79X22.png"
        }
    },
    {
        "email": "mFK5hCRObKiIqguHQ2dxgJB6I0@hotmail.com",
        "password": "FZ<vF'H;T=ysr`,j",
        "response": {
            "appId": "PXaOtQIWNf",
            "jsClientSrc": "/aOtQIWNf/init.js",
            "firstPartyEnabled": true,
            "vid": "4ed03879-33e0-11ef-81a0-c7eb5e4c559b",
            "uuid": "4ea96570-33e0-11ef-a5db-8dbf8345be5d",
            "hostUrl": "/aOtQIWNf/xhr",
            "blockScript": "/aOtQIWNf/captcha/captcha.js?a=c&u=4ea96570-33e0-11ef-a5db-8dbf8345be5d&v=4ed03879-33e0-11ef-81a0-c7eb5e4c559b&m=0",
            "altBlockScript": "https://captcha.px-cloud.net/PXaOtQIWNf/captcha.js?a=c&u=4ea96570-33e0-11ef-a5db-8dbf8345be5d&v=4ed03879-33e0-11ef-81a0-c7eb5e4c559b&m=0",
            "customLogo": "https://chegg-mobile-promotions.cheggcdn.com/px/Chegg-logo-79X22.png"
        }
    },
    {
        "email": "cwbVXOt1CKtaXNmtjmEVDYACmG9D@hotmail.com",
        "password": "[C1)2Ec*g{+vr&4Y",
        "response": {
            "appId": "PXaOtQIWNf",
            "jsClientSrc": "/aOtQIWNf/init.js",
            "firstPartyEnabled": true,
            "vid": "4ed03879-33e0-11ef-81a0-c7eb5e4c559b",
            "uuid": "4ea96570-33e0-11ef-a5db-8dbf8345be5d",
            "hostUrl": "/aOtQIWNf/xhr",
            "blockScript": "/aOtQIWNf/captcha/captcha.js?a=c&u=4ea96570-33e0-11ef-a5db-8dbf8345be5d&v=4ed03879-33e0-11ef-81a0-c7eb5e4c559b&m=0",
            "altBlockScript": "https://captcha.px-cloud.net/PXaOtQIWNf/captcha.js?a=c&u=4ea96570-33e0-11ef-a5db-8dbf8345be5d&v=4ed03879-33e0-11ef-81a0-c7eb5e4c559b&m=0",
            "customLogo": "https://chegg-mobile-promotions.cheggcdn.com/px/Chegg-logo-79X22.png"
        }
    }
][
    {
        "email": "aKEjGmT1eVAuqK935zji@hotmail.com",
        "password": "1}!Qn{Yj+6E<x)/S",
        "response": {
            "appId": "PXaOtQIWNf",
            "jsClientSrc": "/aOtQIWNf/init.js",
            "firstPartyEnabled": true,
            "vid": "4ed03879-33e0-11ef-81a0-c7eb5e4c559b",
            "uuid": "4ea96570-33e0-11ef-a5db-8dbf8345be5d",
            "hostUrl": "/aOtQIWNf/xhr",
            "blockScript": "/aOtQIWNf/captcha/captcha.js?a=c&u=4ea96570-33e0-11ef-a5db-8dbf8345be5d&v=4ed03879-33e0-11ef-81a0-c7eb5e4c559b&m=0",
            "altBlockScript": "https://captcha.px-cloud.net/PXaOtQIWNf/captcha.js?a=c&u=4ea96570-33e0-11ef-a5db-8dbf8345be5d&v=4ed03879-33e0-11ef-81a0-c7eb5e4c559b&m=0",
            "customLogo": "https://chegg-mobile-promotions.cheggcdn.com/px/Chegg-logo-79X22.png"
        }
    },
    {
        "email": "jeUOPWCaAKYYP8KT0fBCx1rSOIwB@hotmail.com",
        "password": "|,eZ3NL4hw_C[;B*",
        "response": {
            "appId": "PXaOtQIWNf",
            "jsClientSrc": "/aOtQIWNf/init.js",
            "firstPartyEnabled": true,
            "vid": "4ed03879-33e0-11ef-81a0-c7eb5e4c559b",
            "uuid": "4ea96570-33e0-11ef-a5db-8dbf8345be5d",
            "hostUrl": "/aOtQIWNf/xhr",
            "blockScript": "/aOtQIWNf/captcha/captcha.js?a=c&u=4ea96570-33e0-11ef-a5db-8dbf8345be5d&v=4ed03879-33e0-11ef-81a0-c7eb5e4c559b&m=0",
            "altBlockScript": "https://captcha.px-cloud.net/PXaOtQIWNf/captcha.js?a=c&u=4ea96570-33e0-11ef-a5db-8dbf8345be5d&v=4ed03879-33e0-11ef-81a0-c7eb5e4c559b&m=0",
            "customLogo": "https://chegg-mobile-promotions.cheggcdn.com/px/Chegg-logo-79X22.png"
        }
    },
    {
        "email": "HWHaeT6dUMgetdfNuUoC5U8y@hotmail.com",
        "password": "\"'SfN2Vy.=h=yP.J",
        "response": {
            "appId": "PXaOtQIWNf",
            "jsClientSrc": "/aOtQIWNf/init.js",
            "firstPartyEnabled": true,
            "vid": "4ed03879-33e0-11ef-81a0-c7eb5e4c559b",
            "uuid": "4ea96570-33e0-11ef-a5db-8dbf8345be5d",
            "hostUrl": "/aOtQIWNf/xhr",
            "blockScript": "/aOtQIWNf/captcha/captcha.js?a=c&u=4ea96570-33e0-11ef-a5db-8dbf8345be5d&v=4ed03879-33e0-11ef-81a0-c7eb5e4c559b&m=0",
            "altBlockScript": "https://captcha.px-cloud.net/PXaOtQIWNf/captcha.js?a=c&u=4ea96570-33e0-11ef-a5db-8dbf8345be5d&v=4ed03879-33e0-11ef-81a0-c7eb5e4c559b&m=0",
            "customLogo": "https://chegg-mobile-promotions.cheggcdn.com/px/Chegg-logo-79X22.png"
        }
    },
    {
        "email": "JPBrMvxaYK9CuAUVKRLJkDXHk@hotmail.com",
        "password": "!#{\"uFrW]2XR1u1+",
        "response": {
            "appId": "PXaOtQIWNf",
            "jsClientSrc": "/aOtQIWNf/init.js",
            "firstPartyEnabled": true,
            "vid": "4ed03879-33e0-11ef-81a0-c7eb5e4c559b",
            "uuid": "4ea96570-33e0-11ef-a5db-8dbf8345be5d",
            "hostUrl": "/aOtQIWNf/xhr",
            "blockScript": "/aOtQIWNf/captcha/captcha.js?a=c&u=4ea96570-33e0-11ef-a5db-8dbf8345be5d&v=4ed03879-33e0-11ef-81a0-c7eb5e4c559b&m=0",
            "altBlockScript": "https://captcha.px-cloud.net/PXaOtQIWNf/captcha.js?a=c&u=4ea96570-33e0-11ef-a5db-8dbf8345be5d&v=4ed03879-33e0-11ef-81a0-c7eb5e4c559b&m=0",
            "customLogo": "https://chegg-mobile-promotions.cheggcdn.com/px/Chegg-logo-79X22.png"
        }
    },
    {
        "email": "y9vTAR9yaBfzdVoLcXqYQ0AF@hotmail.com",
        "password": "LT<%N1wy`^YerVzj",
        "response": {
            "appId": "PXaOtQIWNf",
            "jsClientSrc": "/aOtQIWNf/init.js",
            "firstPartyEnabled": true,
            "vid": "4ed03879-33e0-11ef-81a0-c7eb5e4c559b",
            "uuid": "4ea96570-33e0-11ef-a5db-8dbf8345be5d",
            "hostUrl": "/aOtQIWNf/xhr",
            "blockScript": "/aOtQIWNf/captcha/captcha.js?a=c&u=4ea96570-33e0-11ef-a5db-8dbf8345be5d&v=4ed03879-33e0-11ef-81a0-c7eb5e4c559b&m=0",
            "altBlockScript": "https://captcha.px-cloud.net/PXaOtQIWNf/captcha.js?a=c&u=4ea96570-33e0-11ef-a5db-8dbf8345be5d&v=4ed03879-33e0-11ef-81a0-c7eb5e4c559b&m=0",
            "customLogo": "https://chegg-mobile-promotions.cheggcdn.com/px/Chegg-logo-79X22.png"
        }
    }
][
    {
        "email": "sMrJrR9Bf6dQahPyADNAqDG@hotmail.com",
        "password": "E[dLg~BY:{Z.0FN<",
        "response": {
            "data": {
                "signUpUser": {
                    "tokens": {
                        "idToken": "eyJhbGciOiJSUzI1NiIsInR5cCI6IkpXVCJ9.eyJlbWFpbCI6InNNckpyUjlCZjZkUWFoUHlBRE5BcURHQGhvdG1haWwuY29tIiwiaXNzIjoiaHViLmNoZWdnLmNvbSIsImF1ZCI6IkNIR0ciLCJpYXQiOjE3MTk0MzE3MjMsImV4cCI6MTczNDk4MzcyMywic3ViIjoiMWFiMWMyMTAtNzc3Mi00NmQzLWJlNmQtMzM4YjMyODU2YmU2IiwicmVwYWNrZXJfaWQiOiJhcHciLCJjdHlwIjoiaWQiLCJpZHNpZCI6ImIzYTJhZTNjIiwiaWRzdCI6MTcxOTQzMTcyMzY5NywiaWRzZyI6InBhc3N3b3JkIn0.BqifkDHJ9Yqy0nVKBxM-flTt8S0323zaayzhG8UZoCyJEirMhjGZTzoj9VfiYcWUzbKcyPI8CCdzFFIC-GlGx_VPZH4w7MVDUY4uTm_TwZ35BSGDdrH6kx2R2xcErBADaC-N6uMjw_mBavb3uVH_1CcD3e8Ww4xfkgxVlRXBvUmSVHEhglGRqUO31ETR29H3MJy4P1uNe7BcZ4AAgg-jN7dbBli_nyDbqIkM8-8WYZ3hlvkTNsfzRd-W7Ia_nLmJ1gRX4Y6Dar55-ZuZFGS0E9L6zIlzImACfDu9KpL-r3n07x8m9GCMfCvFh8t289WbzgfOp8yDeqVvqRLQC5pM3g",
                        "accessToken": "eyJhbGciOiJSUzI1NiIsInR5cCI6IkpXVCJ9.eyJpc3MiOiJodWIuY2hlZ2cuY29tIiwic3ViIjoiMWFiMWMyMTAtNzc3Mi00NmQzLWJlNmQtMzM4YjMyODU2YmU2IiwiYXVkIjpbInRlc3QtY2hlZ2ciLCJodHRwczovL2NoZWdnLXByb2QuY2hlZ2cuYXV0aDAuY29tL3VzZXJpbmZvIl0sImlhdCI6MTcxOTQzMTcyMywiZXhwIjoxNzE5NDMzMTYzLCJzY29wZSI6Im9wZW5pZCBwcm9maWxlIGVtYWlsIGFkZHJlc3MgcGhvbmUgb2ZmbGluZV9hY2Nlc3MiLCJndHkiOiJwYXNzd29yZCIsImF6cCI6IkZpcGozYW5GNFV6OE5VWUhPY2JqTE14NnE0elZLRU9lIiwicmVwYWNrZXJfaWQiOiJhcHciLCJjaGdocmQiOnRydWUsImN0eXAiOiJhY2Nlc3MifQ.g5SnOESCshSVOq2wQXcVzghucp_JJ_qAiudXY6yeSiJEz2C4mJ7q12UVdMrXA4gdRr7V7i1-g_tZpDg0bPkrhLMimC3SgAbMVLCmclKqYtzPAskaG_R-5XVZZbwOuXkQFPjNKMl1tR0KnMhUXXYjC59qr3gtgmrA6VYIr41Cqwpvlr2A4JEfpBhomZLLs2NQVD8nLuykYq4bqbnwiYYDJp_08oyzbZBCx1Ao1w012at-imvLvTokJ43aFiK10vKjX1YhPY7_QeiSsXTctHO-WKawq7rcEBgjJrYwr0OYCM0nxz7E3Hm-ZEmkZmjjapXQgFiWhcQALCkUht2LqGxlVQ",
                        "expires": 1440
                    },
                    "encryptedEmail": "+x3xRFJNqgdG6kDo5WDYmF93AF1ATtQkErIAoR8rH1TjcRSG1dQjJQ==",
                    "encryptedCheggId": "fzwYoT7AAkL0w+NrteOaWdawmL2fCVoPp21jtnbR55q3vG8p1rFDNg==",
                    "uuid": "1ab1c210-7772-46d3-be6d-338b32856be6"
                }
            }
        }
    },
    {
        "email": "8MUqRTUKDvbzRVvj1jD6XJrEyt@hotmail.com",
        "password": "@.~D_d~5JSH&5NKa",
        "response": {
            "data": {
                "signUpUser": {
                    "tokens": {
                        "idToken": "eyJhbGciOiJSUzI1NiIsInR5cCI6IkpXVCJ9.eyJlbWFpbCI6IjhNVXFSVFVLRHZielJWdmoxakQ2WEpyRXl0QGhvdG1haWwuY29tIiwiaXNzIjoiaHViLmNoZWdnLmNvbSIsImF1ZCI6IkNIR0ciLCJpYXQiOjE3MTk0MzE3MjUsImV4cCI6MTczNDk4MzcyNSwic3ViIjoiNDQwMzRlY2EtYjFlOC00OWQ3LTgwMGMtMDllNzJiMjQxZThiIiwicmVwYWNrZXJfaWQiOiJhcHciLCJjdHlwIjoiaWQiLCJpZHNpZCI6IjI2ZmE1ODkwIiwiaWRzdCI6MTcxOTQzMTcyNTgxMCwiaWRzZyI6InBhc3N3b3JkIn0.XSCdqg0oqZ_YchVtjV4KNMjIhzt6yE22yaW7NPrsPBBGIt2P23SzlVD8G1kKQA8JU1Y8gdSCF_oL4vCtKczR_c1qw0ypJ3ZFcOPxyD4xLMMb48QXMu8uPMZ_114I1DJKBHpXr5IgxPyHQ37yin3pNfBIx7X-HP9tPTMVwsQA55R5Dj1Y5sX9d3eFgoPvae3ug8B9eSAlHIVwDv3akup_4BuiV2N4C-8qGQq16P_nfOrG7NabgnpPw3MB5y2cLcjsBeZVWpAh1AppdTTnUqv-VtqRY35zBrWjRTNSwHamH7E-V15paDoR4DpYhxjM0XYj6P6lw8KWqgpZqF5Tj2luVw",
                        "accessToken": "eyJhbGciOiJSUzI1NiIsInR5cCI6IkpXVCJ9.eyJpc3MiOiJodWIuY2hlZ2cuY29tIiwic3ViIjoiNDQwMzRlY2EtYjFlOC00OWQ3LTgwMGMtMDllNzJiMjQxZThiIiwiYXVkIjpbInRlc3QtY2hlZ2ciLCJodHRwczovL2NoZWdnLXByb2QuY2hlZ2cuYXV0aDAuY29tL3VzZXJpbmZvIl0sImlhdCI6MTcxOTQzMTcyNSwiZXhwIjoxNzE5NDMzMTY1LCJzY29wZSI6Im9wZW5pZCBwcm9maWxlIGVtYWlsIGFkZHJlc3MgcGhvbmUgb2ZmbGluZV9hY2Nlc3MiLCJndHkiOiJwYXNzd29yZCIsImF6cCI6IkZpcGozYW5GNFV6OE5VWUhPY2JqTE14NnE0elZLRU9lIiwicmVwYWNrZXJfaWQiOiJhcHciLCJjaGdocmQiOnRydWUsImN0eXAiOiJhY2Nlc3MifQ.45ux0Zz51wNcU6wnZaTQgSmq4j-Utusk_6vCwZ_9X9cYxNH4dnebGGz8rW41Vt_d82uDfX4Wd0caKXBJyOyuJmeYyxWLaQSsjgexrXO5n9DK_idM09jtcPbsueUanR3wiwiGKJoaQ5uXBHDdhyz4XkEqndrwFNKCtygIADg0ALPgwou-Q7xYh5ByyuN3lEwlqgJkNk5HRf6im8vP28zRb9fjzejj2BKCzypn3njlQjxiHr9lh_yM9d_2JzEVUtS7BMqzkirvYKxX9dqCJU2Z8-93cS_V4NPVQ65rhucF4ZuoIdhTI7FegQ5y9E2-Zml5zGNC7Q79RVZZr6xsmCkOOw",
                        "expires": 1440
                    },
                    "encryptedEmail": "IcAZdaxy/4TkReHvAAS744X8ccOKQvIRowXes3Tl6gz7c2NA58bmcw==",
                    "encryptedCheggId": "BdVpJFYXrBU81+DwRUWJmANE5WsjSr0PT/IsoPPRh6anMlFZPNLloA==",
                    "uuid": "44034eca-b1e8-49d7-800c-09e72b241e8b"
                }
            }
        }
    },
    {
        "email": "p5ajPXqCF7W9cgH5rlqiGe4@hotmail.com",
        "password": "j\\se<R{\\/wW\"0UP@",
        "response": {
            "appId": "PXaOtQIWNf",
            "jsClientSrc": "/aOtQIWNf/init.js",
            "firstPartyEnabled": true,
            "vid": "4ed03879-33e0-11ef-81a0-c7eb5e4c559b",
            "uuid": "4ea96570-33e0-11ef-a5db-8dbf8345be5d",
            "hostUrl": "/aOtQIWNf/xhr",
            "blockScript": "/aOtQIWNf/captcha/captcha.js?a=c&u=4ea96570-33e0-11ef-a5db-8dbf8345be5d&v=4ed03879-33e0-11ef-81a0-c7eb5e4c559b&m=0",
            "altBlockScript": "https://captcha.px-cloud.net/PXaOtQIWNf/captcha.js?a=c&u=4ea96570-33e0-11ef-a5db-8dbf8345be5d&v=4ed03879-33e0-11ef-81a0-c7eb5e4c559b&m=0",
            "customLogo": "https://chegg-mobile-promotions.cheggcdn.com/px/Chegg-logo-79X22.png"
        }
    },
    {
        "email": "sQkQ5Vb6804jFQQApNII7zm7y8@hotmail.com",
        "password": "-\\[@HDR{}w[2|:vM",
        "response": {
            "appId": "PXaOtQIWNf",
            "jsClientSrc": "/aOtQIWNf/init.js",
            "firstPartyEnabled": true,
            "vid": "4ed03879-33e0-11ef-81a0-c7eb5e4c559b",
            "uuid": "4ea96570-33e0-11ef-a5db-8dbf8345be5d",
            "hostUrl": "/aOtQIWNf/xhr",
            "blockScript": "/aOtQIWNf/captcha/captcha.js?a=c&u=4ea96570-33e0-11ef-a5db-8dbf8345be5d&v=4ed03879-33e0-11ef-81a0-c7eb5e4c559b&m=0",
            "altBlockScript": "https://captcha.px-cloud.net/PXaOtQIWNf/captcha.js?a=c&u=4ea96570-33e0-11ef-a5db-8dbf8345be5d&v=4ed03879-33e0-11ef-81a0-c7eb5e4c559b&m=0",
            "customLogo": "https://chegg-mobile-promotions.cheggcdn.com/px/Chegg-logo-79X22.png"
        }
    },
    {
        "email": "swmuDITbCDk3NG3jVtpVQhhUJi0@hotmail.com",
        "password": "oE9Kv.D`;eIJ#s\\l",
        "response": {
            "appId": "PXaOtQIWNf",
            "jsClientSrc": "/aOtQIWNf/init.js",
            "firstPartyEnabled": true,
            "vid": "4ed03879-33e0-11ef-81a0-c7eb5e4c559b",
            "uuid": "4ea96570-33e0-11ef-a5db-8dbf8345be5d",
            "hostUrl": "/aOtQIWNf/xhr",
            "blockScript": "/aOtQIWNf/captcha/captcha.js?a=c&u=4ea96570-33e0-11ef-a5db-8dbf8345be5d&v=4ed03879-33e0-11ef-81a0-c7eb5e4c559b&m=0",
            "altBlockScript": "https://captcha.px-cloud.net/PXaOtQIWNf/captcha.js?a=c&u=4ea96570-33e0-11ef-a5db-8dbf8345be5d&v=4ed03879-33e0-11ef-81a0-c7eb5e4c559b&m=0",
            "customLogo": "https://chegg-mobile-promotions.cheggcdn.com/px/Chegg-logo-79X22.png"
        }
    }
][
    {
        "email": "NCt68EIA7j6gjqlm6C7efIaJsy@hotmail.com",
        "password": "`Hb|</~/RWL4TNr-",
        "response": {
            "appId": "PXaOtQIWNf",
            "jsClientSrc": "/aOtQIWNf/init.js",
            "firstPartyEnabled": true,
            "uuid": "408146a3-33f6-11ef-9ef1-f74952d687e0",
            "hostUrl": "/aOtQIWNf/xhr",
            "blockScript": "/aOtQIWNf/captcha/captcha.js?a=c&u=408146a3-33f6-11ef-9ef1-f74952d687e0&v=&m=0",
            "altBlockScript": "https://captcha.px-cloud.net/PXaOtQIWNf/captcha.js?a=c&u=408146a3-33f6-11ef-9ef1-f74952d687e0&v=&m=0",
            "customLogo": "https://chegg-mobile-promotions.cheggcdn.com/px/Chegg-logo-79X22.png"
        }
    },
    {
        "email": "CMBLG96Q1adSkInursXKfsrCq93O@hotmail.com",
        "password": "YC.Cr}6_@&u6,HkX",
        "response": {
            "appId": "PXaOtQIWNf",
            "jsClientSrc": "/aOtQIWNf/init.js",
            "firstPartyEnabled": true,
            "uuid": "4135912f-33f6-11ef-a0cb-6be57f1f07c3",
            "hostUrl": "/aOtQIWNf/xhr",
            "blockScript": "/aOtQIWNf/captcha/captcha.js?a=c&u=4135912f-33f6-11ef-a0cb-6be57f1f07c3&v=&m=0",
            "altBlockScript": "https://captcha.px-cloud.net/PXaOtQIWNf/captcha.js?a=c&u=4135912f-33f6-11ef-a0cb-6be57f1f07c3&v=&m=0",
            "customLogo": "https://chegg-mobile-promotions.cheggcdn.com/px/Chegg-logo-79X22.png"
        }
    },
    {
        "email": "6hqZoFWMOQUt9XaVVCHNp7@hotmail.com",
        "password": ":HHV':m~8)J,(dit",
        "response": {
            "appId": "PXaOtQIWNf",
            "jsClientSrc": "/aOtQIWNf/init.js",
            "firstPartyEnabled": true,
            "uuid": "41eb4c2e-33f6-11ef-ad2b-fe3930b39e1a",
            "hostUrl": "/aOtQIWNf/xhr",
            "blockScript": "/aOtQIWNf/captcha/captcha.js?a=c&u=41eb4c2e-33f6-11ef-ad2b-fe3930b39e1a&v=&m=0",
            "altBlockScript": "https://captcha.px-cloud.net/PXaOtQIWNf/captcha.js?a=c&u=41eb4c2e-33f6-11ef-ad2b-fe3930b39e1a&v=&m=0",
            "customLogo": "https://chegg-mobile-promotions.cheggcdn.com/px/Chegg-logo-79X22.png"
        }
    },
    {
        "email": "iZfjFZ9cyaZgiLLLzKgbTo@hotmail.com",
        "password": "T,$+((IKUS7-VgJo",
        "response": {
            "appId": "PXaOtQIWNf",
            "jsClientSrc": "/aOtQIWNf/init.js",
            "firstPartyEnabled": true,
            "uuid": "429d511c-33f6-11ef-a053-f74952d687e0",
            "hostUrl": "/aOtQIWNf/xhr",
            "blockScript": "/aOtQIWNf/captcha/captcha.js?a=c&u=429d511c-33f6-11ef-a053-f74952d687e0&v=&m=0",
            "altBlockScript": "https://captcha.px-cloud.net/PXaOtQIWNf/captcha.js?a=c&u=429d511c-33f6-11ef-a053-f74952d687e0&v=&m=0",
            "customLogo": "https://chegg-mobile-promotions.cheggcdn.com/px/Chegg-logo-79X22.png"
        }
    },
    {
        "email": "HsY64gABz8rYZZdlrn7P2ZS0QQp@hotmail.com",
        "password": "uOqe;4D?*&Gbn3%?",
        "response": {
            "appId": "PXaOtQIWNf",
            "jsClientSrc": "/aOtQIWNf/init.js",
            "firstPartyEnabled": true,
            "uuid": "434ddf75-33f6-11ef-ac53-cc794f158a3f",
            "hostUrl": "/aOtQIWNf/xhr",
            "blockScript": "/aOtQIWNf/captcha/captcha.js?a=c&u=434ddf75-33f6-11ef-ac53-cc794f158a3f&v=&m=0",
            "altBlockScript": "https://captcha.px-cloud.net/PXaOtQIWNf/captcha.js?a=c&u=434ddf75-33f6-11ef-ac53-cc794f158a3f&v=&m=0",
            "customLogo": "https://chegg-mobile-promotions.cheggcdn.com/px/Chegg-logo-79X22.png"
        }
    }
][
    {
        "email": "HIAYZVfu7043kueXEEwPoG1RWyr@hotmail.com",
        "password": "-SK%^Pf8@o^U`TMA",
        "response": {
            "data": {
                "signUpUser": {
                    "tokens": {
                        "idToken": "eyJhbGciOiJSUzI1NiIsInR5cCI6IkpXVCJ9.eyJlbWFpbCI6IkhJQVlaVmZ1NzA0M2t1ZVhFRXdQb0cxUld5ckBob3RtYWlsLmNvbSIsImlzcyI6Imh1Yi5jaGVnZy5jb20iLCJhdWQiOiJDSEdHIiwiaWF0IjoxNzE5NDczNDY0LCJleHAiOjE3MzUwMjU0NjQsInN1YiI6ImM5ZjdmNTU0LTY5MDgtNGY4NS1iYzRhLTMwMjk0Zjg3YmE5MCIsInJlcGFja2VyX2lkIjoiYXB3IiwiY3R5cCI6ImlkIiwiaWRzaWQiOiI3NmY3NzYxZiIsImlkc3QiOjE3MTk0NzM0NjQzNTEsImlkc2ciOiJwYXNzd29yZCJ9.SmdjTuqnRduy2ExSPofj8a48Jg7yK7RaZOERPM4d2CZO7udkYtxw3xxVLgj7oTTqjabGRLR_aTvWr6xAzosTVi9aUzrB6sOXRpQOgRX3tO-TJy8VIAq4Uc0T0pzWGFIvu6Jq8XM3BwdvBDtZEN-Xy-9uhWtsW4P_YVBsymql-_U10dwOqiYdtfuBIzJoXQR_qzDsHke-AzVnV5gtqjCQGMwHq95ZgS5s8WsRNTvHT_pYi5Dxo1biB7CUEFF9eMhs3WRdGUC0KiSH8Va7KgOjqOQaXoVhlbdxzczvhJxqX-xZNtKNCR2zQ80nXg4YHvug-M-5UlHeP9NL3VXQTLYwgg",
                        "accessToken": "eyJhbGciOiJSUzI1NiIsInR5cCI6IkpXVCJ9.eyJpc3MiOiJodWIuY2hlZ2cuY29tIiwic3ViIjoiYzlmN2Y1NTQtNjkwOC00Zjg1LWJjNGEtMzAyOTRmODdiYTkwIiwiYXVkIjpbInRlc3QtY2hlZ2ciLCJodHRwczovL2NoZWdnLXByb2QuY2hlZ2cuYXV0aDAuY29tL3VzZXJpbmZvIl0sImlhdCI6MTcxOTQ3MzQ2NCwiZXhwIjoxNzE5NDc0OTA0LCJzY29wZSI6Im9wZW5pZCBwcm9maWxlIGVtYWlsIGFkZHJlc3MgcGhvbmUgb2ZmbGluZV9hY2Nlc3MiLCJndHkiOiJwYXNzd29yZCIsImF6cCI6IkZpcGozYW5GNFV6OE5VWUhPY2JqTE14NnE0elZLRU9lIiwicmVwYWNrZXJfaWQiOiJhcHciLCJjaGdocmQiOnRydWUsImN0eXAiOiJhY2Nlc3MifQ.zLvQVR1se77HqYHaEvhFpm3X1mA18-udhRuW2r6gUAVCzGv0ED880Lm_gvB-SZEzFcpVb74u135AJIhOjs8enE2KcDttmf9r27XnAQA6xkDVTkhUlB2RoR9T808EdvKo6yN1uHNAEp-3nucESJz9fUwXl6H_I7x0rHZaMoMgyiUpp_DloWTGIy4BSysYyhG6peV66Ak1shtbgnReejxc9nVB7sB_3RVuGs5XGUjMzho45qvfkJc-TVg67LyQn6bEAZkgZlNxM42zrNdgMUMer9N3z-fxq1lt3Q78rrOJsY-jhyZ97I9Rl4DdS9T6KYva0H0-DVoqXEB5YlbyvsSkRA",
                        "expires": 1440
                    },
                    "encryptedEmail": "1B2M5i+d+at9fKaSPD3lZDNlGuldRJlXn+LRirQqEk8OaNu2ug4zwCqVaMntuI2c",
                    "encryptedCheggId": "YPZ0yLtqaQeLy2SetRv50mmV9/EVJuoh/sSRvAsFwYrOwxqEmW/EiA==",
                    "uuid": "c9f7f554-6908-4f85-bc4a-30294f87ba90"
                }
            }
        }
    },
    {
        "email": "M3X0kXSFQSMSprxMAFCKd@hotmail.com",
        "password": "sC!7Yo/g[pav@\"31",
        "response": {
            "appId": "PXaOtQIWNf",
            "jsClientSrc": "/aOtQIWNf/init.js",
            "firstPartyEnabled": true,
            "vid": "4ed03879-33e0-11ef-81a0-c7eb5e4c559b",
            "uuid": "4ea96570-33e0-11ef-a5db-8dbf8345be5d",
            "hostUrl": "/aOtQIWNf/xhr",
            "blockScript": "/aOtQIWNf/captcha/captcha.js?a=c&u=4ea96570-33e0-11ef-a5db-8dbf8345be5d&v=4ed03879-33e0-11ef-81a0-c7eb5e4c559b&m=0",
            "altBlockScript": "https://captcha.px-cloud.net/PXaOtQIWNf/captcha.js?a=c&u=4ea96570-33e0-11ef-a5db-8dbf8345be5d&v=4ed03879-33e0-11ef-81a0-c7eb5e4c559b&m=0",
            "customLogo": "https://chegg-mobile-promotions.cheggcdn.com/px/Chegg-logo-79X22.png"
        }
    },
    {
        "email": "wusSiZdlEnhVndLf4GzEuxIBZQR@hotmail.com",
        "password": "e$8h~WWX><K2.}XK",
        "response": {
            "appId": "PXaOtQIWNf",
            "jsClientSrc": "/aOtQIWNf/init.js",
            "firstPartyEnabled": true,
            "vid": "4ed03879-33e0-11ef-81a0-c7eb5e4c559b",
            "uuid": "4ea96570-33e0-11ef-a5db-8dbf8345be5d",
            "hostUrl": "/aOtQIWNf/xhr",
            "blockScript": "/aOtQIWNf/captcha/captcha.js?a=c&u=4ea96570-33e0-11ef-a5db-8dbf8345be5d&v=4ed03879-33e0-11ef-81a0-c7eb5e4c559b&m=0",
            "altBlockScript": "https://captcha.px-cloud.net/PXaOtQIWNf/captcha.js?a=c&u=4ea96570-33e0-11ef-a5db-8dbf8345be5d&v=4ed03879-33e0-11ef-81a0-c7eb5e4c559b&m=0",
            "customLogo": "https://chegg-mobile-promotions.cheggcdn.com/px/Chegg-logo-79X22.png"
        }
    },
    {
        "email": "kY9btG22lr1PkvFt9pkHcAKJ@hotmail.com",
        "password": "ns0d{$AQQkJ&BKCC",
        "response": {
            "appId": "PXaOtQIWNf",
            "jsClientSrc": "/aOtQIWNf/init.js",
            "firstPartyEnabled": true,
            "vid": "4ed03879-33e0-11ef-81a0-c7eb5e4c559b",
            "uuid": "4ea96570-33e0-11ef-a5db-8dbf8345be5d",
            "hostUrl": "/aOtQIWNf/xhr",
            "blockScript": "/aOtQIWNf/captcha/captcha.js?a=c&u=4ea96570-33e0-11ef-a5db-8dbf8345be5d&v=4ed03879-33e0-11ef-81a0-c7eb5e4c559b&m=0",
            "altBlockScript": "https://captcha.px-cloud.net/PXaOtQIWNf/captcha.js?a=c&u=4ea96570-33e0-11ef-a5db-8dbf8345be5d&v=4ed03879-33e0-11ef-81a0-c7eb5e4c559b&m=0",
            "customLogo": "https://chegg-mobile-promotions.cheggcdn.com/px/Chegg-logo-79X22.png"
        }
    },
    {
        "email": "JenWupRVVCS6GEexvnTSH9@hotmail.com",
        "password": "|}MPV6>`m2BN2MN$",
        "response": {
            "appId": "PXaOtQIWNf",
            "jsClientSrc": "/aOtQIWNf/init.js",
            "firstPartyEnabled": true,
            "vid": "4ed03879-33e0-11ef-81a0-c7eb5e4c559b",
            "uuid": "4ea96570-33e0-11ef-a5db-8dbf8345be5d",
            "hostUrl": "/aOtQIWNf/xhr",
            "blockScript": "/aOtQIWNf/captcha/captcha.js?a=c&u=4ea96570-33e0-11ef-a5db-8dbf8345be5d&v=4ed03879-33e0-11ef-81a0-c7eb5e4c559b&m=0",
            "altBlockScript": "https://captcha.px-cloud.net/PXaOtQIWNf/captcha.js?a=c&u=4ea96570-33e0-11ef-a5db-8dbf8345be5d&v=4ed03879-33e0-11ef-81a0-c7eb5e4c559b&m=0",
            "customLogo": "https://chegg-mobile-promotions.cheggcdn.com/px/Chegg-logo-79X22.png"
        }
    }
][
    {
        "email": "rFSotfkJSQYjDIr8M9CYEjoXCw@hotmail.com",
        "password": "K'F&sxa*eblq'}1x",
        "response": {
            "appId": "PXaOtQIWNf",
            "jsClientSrc": "/aOtQIWNf/init.js",
            "firstPartyEnabled": true,
            "vid": "4ed03879-33e0-11ef-81a0-c7eb5e4c559b",
            "uuid": "4ea96570-33e0-11ef-a5db-8dbf8345be5d",
            "hostUrl": "/aOtQIWNf/xhr",
            "blockScript": "/aOtQIWNf/captcha/captcha.js?a=c&u=4ea96570-33e0-11ef-a5db-8dbf8345be5d&v=4ed03879-33e0-11ef-81a0-c7eb5e4c559b&m=0",
            "altBlockScript": "https://captcha.px-cloud.net/PXaOtQIWNf/captcha.js?a=c&u=4ea96570-33e0-11ef-a5db-8dbf8345be5d&v=4ed03879-33e0-11ef-81a0-c7eb5e4c559b&m=0",
            "customLogo": "https://chegg-mobile-promotions.cheggcdn.com/px/Chegg-logo-79X22.png"
        }
    },
    {
        "email": "dXipdtjRs2PJNHTIc0NU@hotmail.com",
        "password": "l(+lu.@qjcq)p6&C",
        "response": {
            "appId": "PXaOtQIWNf",
            "jsClientSrc": "/aOtQIWNf/init.js",
            "firstPartyEnabled": true,
            "vid": "4ed03879-33e0-11ef-81a0-c7eb5e4c559b",
            "uuid": "4ea96570-33e0-11ef-a5db-8dbf8345be5d",
            "hostUrl": "/aOtQIWNf/xhr",
            "blockScript": "/aOtQIWNf/captcha/captcha.js?a=c&u=4ea96570-33e0-11ef-a5db-8dbf8345be5d&v=4ed03879-33e0-11ef-81a0-c7eb5e4c559b&m=0",
            "altBlockScript": "https://captcha.px-cloud.net/PXaOtQIWNf/captcha.js?a=c&u=4ea96570-33e0-11ef-a5db-8dbf8345be5d&v=4ed03879-33e0-11ef-81a0-c7eb5e4c559b&m=0",
            "customLogo": "https://chegg-mobile-promotions.cheggcdn.com/px/Chegg-logo-79X22.png"
        }
    },
    {
        "email": "bxyGYjeGU2mZ2ZfkYeWXnfDLRX@hotmail.com",
        "password": "iSOs^%XO4QPb_m7y",
        "response": {
            "appId": "PXaOtQIWNf",
            "jsClientSrc": "/aOtQIWNf/init.js",
            "firstPartyEnabled": true,
            "vid": "4ed03879-33e0-11ef-81a0-c7eb5e4c559b",
            "uuid": "4ea96570-33e0-11ef-a5db-8dbf8345be5d",
            "hostUrl": "/aOtQIWNf/xhr",
            "blockScript": "/aOtQIWNf/captcha/captcha.js?a=c&u=4ea96570-33e0-11ef-a5db-8dbf8345be5d&v=4ed03879-33e0-11ef-81a0-c7eb5e4c559b&m=0",
            "altBlockScript": "https://captcha.px-cloud.net/PXaOtQIWNf/captcha.js?a=c&u=4ea96570-33e0-11ef-a5db-8dbf8345be5d&v=4ed03879-33e0-11ef-81a0-c7eb5e4c559b&m=0",
            "customLogo": "https://chegg-mobile-promotions.cheggcdn.com/px/Chegg-logo-79X22.png"
        }
    },
    {
        "email": "8vM9FmozTagKxph8lPJP2pv8Td8@hotmail.com",
        "password": "]T7v`ZM(0isF&_.T",
        "response": {
            "appId": "PXaOtQIWNf",
            "jsClientSrc": "/aOtQIWNf/init.js",
            "firstPartyEnabled": true,
            "vid": "4ed03879-33e0-11ef-81a0-c7eb5e4c559b",
            "uuid": "4ea96570-33e0-11ef-a5db-8dbf8345be5d",
            "hostUrl": "/aOtQIWNf/xhr",
            "blockScript": "/aOtQIWNf/captcha/captcha.js?a=c&u=4ea96570-33e0-11ef-a5db-8dbf8345be5d&v=4ed03879-33e0-11ef-81a0-c7eb5e4c559b&m=0",
            "altBlockScript": "https://captcha.px-cloud.net/PXaOtQIWNf/captcha.js?a=c&u=4ea96570-33e0-11ef-a5db-8dbf8345be5d&v=4ed03879-33e0-11ef-81a0-c7eb5e4c559b&m=0",
            "customLogo": "https://chegg-mobile-promotions.cheggcdn.com/px/Chegg-logo-79X22.png"
        }
    },
    {
        "email": "AUeGflUNJisxPgs8ot0holLl5N@hotmail.com",
        "password": "=lxo#@!dAgQBZ9`E",
        "response": {
            "appId": "PXaOtQIWNf",
            "jsClientSrc": "/aOtQIWNf/init.js",
            "firstPartyEnabled": true,
            "vid": "4ed03879-33e0-11ef-81a0-c7eb5e4c559b",
            "uuid": "4ea96570-33e0-11ef-a5db-8dbf8345be5d",
            "hostUrl": "/aOtQIWNf/xhr",
            "blockScript": "/aOtQIWNf/captcha/captcha.js?a=c&u=4ea96570-33e0-11ef-a5db-8dbf8345be5d&v=4ed03879-33e0-11ef-81a0-c7eb5e4c559b&m=0",
            "altBlockScript": "https://captcha.px-cloud.net/PXaOtQIWNf/captcha.js?a=c&u=4ea96570-33e0-11ef-a5db-8dbf8345be5d&v=4ed03879-33e0-11ef-81a0-c7eb5e4c559b&m=0",
            "customLogo": "https://chegg-mobile-promotions.cheggcdn.com/px/Chegg-logo-79X22.png"
        }
    }
][
    {
        "email": "0lrRviuWbWbCbenAP84NAQAae5@hotmail.com",
        "password": "5VmKEJc~2T+oI6(q",
        "response": {
            "data": {
                "signUpUser": {
                    "tokens": {
                        "idToken": "eyJhbGciOiJSUzI1NiIsInR5cCI6IkpXVCJ9.eyJlbWFpbCI6IjBsclJ2aXVXYldiQ2JlbkFQODROQVFBYWU1QGhvdG1haWwuY29tIiwiaXNzIjoiaHViLmNoZWdnLmNvbSIsImF1ZCI6IkNIR0ciLCJpYXQiOjE3MTk0NzUwODUsImV4cCI6MTczNTAyNzA4NSwic3ViIjoiNWEwMzY3NmUtNzYyZi00OWY5LTllMjEtMGRlODc4M2VhNmY3IiwicmVwYWNrZXJfaWQiOiJhcHciLCJjdHlwIjoiaWQiLCJpZHNpZCI6IjExM2ZiYjAyIiwiaWRzdCI6MTcxOTQ3NTA4NTEzMSwiaWRzZyI6InBhc3N3b3JkIn0.wUm9Yrv-BlKlpdRDskYZy2U2J5sSdVeLlDo_gpZZMzcWF2WQWIN05rB58jLeNSynVH9zIrNEpsjzOggBEsInBOWnIT6svRiswWhMPamdNfF0gCp6cNV80imAekr2AXHjuTtGb0pmokAc1K58bTYv1U8Tx-Wk8jIXdx2uJiLRuIcGjQLL9eakDXeYsTXiNrmx0S_E65dHhw0NTZw-n4rkR2Ym6zvIb_8UGzogL6_HiMsaO-2NG_HboEqmnFda5SSqxN-WuaywguxKkOYS8HwIQAIqf7oPJhMFiV_bjjbzUdXfY6VttqyW2eDVkfCNjxJJl6n7eANFI9f-NSvIKtd-hw",
                        "accessToken": "eyJhbGciOiJSUzI1NiIsInR5cCI6IkpXVCJ9.eyJpc3MiOiJodWIuY2hlZ2cuY29tIiwic3ViIjoiNWEwMzY3NmUtNzYyZi00OWY5LTllMjEtMGRlODc4M2VhNmY3IiwiYXVkIjpbInRlc3QtY2hlZ2ciLCJodHRwczovL2NoZWdnLXByb2QuY2hlZ2cuYXV0aDAuY29tL3VzZXJpbmZvIl0sImlhdCI6MTcxOTQ3NTA4NSwiZXhwIjoxNzE5NDc2NTI1LCJzY29wZSI6Im9wZW5pZCBwcm9maWxlIGVtYWlsIGFkZHJlc3MgcGhvbmUgb2ZmbGluZV9hY2Nlc3MiLCJndHkiOiJwYXNzd29yZCIsImF6cCI6IkZpcGozYW5GNFV6OE5VWUhPY2JqTE14NnE0elZLRU9lIiwicmVwYWNrZXJfaWQiOiJhcHciLCJjaGdocmQiOnRydWUsImN0eXAiOiJhY2Nlc3MifQ.yad6AhvxdVTJR-8iznoQ50NJFSUYBgzPIsCKmHXy3Xh_n193IDq8Xs1nBbgW2UcFTqzsN3LvY6bq3XMr4iagNwBEXOoTm7mYTRpi1WlSCxlYQ-ZhpnXOt4kOYOOcjvbet3jZ1LFSPDtRggFgXtMzrLy8BNrRHF_ka2jBQIIHfZW3tr59DH9P0beN1NkDh7AJbvxYZfH6aGL93TV9yd792eQX9alAYmAx7baTwWvXu4gbZ3IgamR4FeqrLxUNmT26ebtKpPUewusTa0NFPfzwpPgbjuwVGV0YbWGI8ifPAQAS1frI-OVDloybVZ7WxRXvJ7KZZd8xNBZQIoMthL2sGg",
                        "expires": 1440
                    },
                    "encryptedEmail": "3ufzOCHsqQJq036FEa+WWTRgyapdUZgWMkI8xwl3js/XIrVhrU/2EA==",
                    "encryptedCheggId": "Y9q1nrMoOfXBMD2XcCCY8wt6RA0YEaHld6PDEa9DZExuCmYkjAY4gA==",
                    "uuid": "5a03676e-762f-49f9-9e21-0de8783ea6f7"
                }
            }
        }
    },
    {
        "email": "XsHeI2KSw0LCc4yRch5Z@hotmail.com",
        "password": "rpweu(V&oK<e}{@T",
        "response": {
            "data": {
                "signUpUser": {
                    "tokens": {
                        "idToken": "eyJhbGciOiJSUzI1NiIsInR5cCI6IkpXVCJ9.eyJlbWFpbCI6IlhzSGVJMktTdzBMQ2M0eVJjaDVaQGhvdG1haWwuY29tIiwiaXNzIjoiaHViLmNoZWdnLmNvbSIsImF1ZCI6IkNIR0ciLCJpYXQiOjE3MTk0NzUwODksImV4cCI6MTczNTAyNzA4OSwic3ViIjoiYmYzYzNkNDItNWM1Zi00MzQwLTg3N2YtMzgwMGIxZjViYmEyIiwicmVwYWNrZXJfaWQiOiJhcHciLCJjdHlwIjoiaWQiLCJpZHNpZCI6Ijg3MDIyODM3IiwiaWRzdCI6MTcxOTQ3NTA4OTc1NSwiaWRzZyI6InBhc3N3b3JkIn0.Rmv9xu3ZgEhZCYCt5DBU2Rh_Ue4UzhoIOvRWRXIT5sP7NY4zo-vTbk1XGpK5jRGbclMDsSMrnsTFs8TRrd5c2Wu-F8A4M_0LRZwCJ3D7Z7Z0OjNOy7vTJIOSNOV0_1oaQPCacIlZnQAzU0qy6p8MC74418YpPldj7xwQvKqCF2pW00Xfj0pEeYUYtRxYMKMddIUv4v1ARsfqvU00r7TACscqHNcNX0Ji1P16X1-J0_iFn-OrzdG5Al3J2sQSn4kv5AjMN6LmTtfq7tfCzX9gssywRSKSRMRBh8aP0t7CUkckMBVwM-RK5aySjUgFJFYSpRQNiBoAe6MgnepGAVXAww",
                        "accessToken": "eyJhbGciOiJSUzI1NiIsInR5cCI6IkpXVCJ9.eyJpc3MiOiJodWIuY2hlZ2cuY29tIiwic3ViIjoiYmYzYzNkNDItNWM1Zi00MzQwLTg3N2YtMzgwMGIxZjViYmEyIiwiYXVkIjpbInRlc3QtY2hlZ2ciLCJodHRwczovL2NoZWdnLXByb2QuY2hlZ2cuYXV0aDAuY29tL3VzZXJpbmZvIl0sImlhdCI6MTcxOTQ3NTA4OSwiZXhwIjoxNzE5NDc2NTI5LCJzY29wZSI6Im9wZW5pZCBwcm9maWxlIGVtYWlsIGFkZHJlc3MgcGhvbmUgb2ZmbGluZV9hY2Nlc3MiLCJndHkiOiJwYXNzd29yZCIsImF6cCI6IkZpcGozYW5GNFV6OE5VWUhPY2JqTE14NnE0elZLRU9lIiwicmVwYWNrZXJfaWQiOiJhcHciLCJjaGdocmQiOnRydWUsImN0eXAiOiJhY2Nlc3MifQ.5vlcZGxzra0s-VqARkZwIXogX2XEpdJxLvR-g5JbTbSQbvKupbNgLn99CsI25Th_8kLr5XL4W_J_TCIlbxcYLpq9PS6JpkTSyoAEk93L-47YZ3wfX735hw_RwRo07biesi5iogxkSfJ4tIRySbwlpOJobrDYI2KwmhxmShqJ3HfofWIM4xeZS-mexH7mVWphOpSM1U9DXExoghfIOjfiF-Z5-Ok7-QudPazsbVpzDO4gBl1vGY25kmHf6oQRIArlwNAfE2ZhzMBAdRs6jOhMIhBk75nnbZ4e7JfCyCmzk6cAd9gZi61b3qm450so39kukRacpb9jjkHMn7WXaAGDWQ",
                        "expires": 1440
                    },
                    "encryptedEmail": "2D6Hz6AaHRtECQ+ZrxwR/Q2n3UurXMKC0dPtdvCLe1ixYo3vzVBPFg==",
                    "encryptedCheggId": "Sm7dOlao28T5PDwFbjLopROt+i8DneJ/VlCshIV8iGfZkyUqZldz1w==",
                    "uuid": "bf3c3d42-5c5f-4340-877f-3800b1f5bba2"
                }
            }
        }
    }
]